{
    "name": "tree name 12",
    "type": "node type 0",
    "id": "tn12",
    "children": [
        {
            "name": "node name 0",
            "type": "node type 5",
            "id": "tn12A"
        },
        {
            "name": "node name 1",
            "type": "node type 6",
            "id": "tn12B"
        },
        {
            "name": "node name 2",
            "type": "node type 2",
            "id": "tn12C"
        },
        {
            "name": "node name 3",
            "type": "node type 3",
            "id": "tn12D",
            "children": [
                {
                    "name": "node name 4",
                    "type": "node type 5",
                    "id": "tn12D0",
                    "children": [
                        {
                            "name": "node name 5",
                            "type": "node type 7",
                            "id": "tn12D0A"
                        }
                    ]
                },
                {
                    "name": "node name 6",
                    "type": "node type 7",
                    "id": "tn12D1"
                }
            ]
        },
        {
            "name": "node name 7",
            "type": "node type 4",
            "id": "tn12E"
        },
        {
            "name": "node name 8",
            "type": "node type 2",
            "id": "tn12F",
            "children": [
                {
                    "name": "node name 9",
                    "type": "node type 7",
                    "id": "tn12F0",
                    "children": [
                        {
                            "name": "node name 10",
                            "type": "node type 6",
                            "id": "tn12F0A",
                            "children": [
                                {
                                    "name": "node name 11",
                                    "type": "node type 4",
                                    "id": "tn12F0A0",
                                    "children": [
                                        {
                                            "name": "node name 12",
                                            "type": "node type 5",
                                            "id": "tn12F0A0A",
                                            "children": [
                                                {
                                                    "name": "node name 13",
                                                    "type": "node type 1",
                                                    "id": "tn12F0A0A0",
                                                    "children": [
                                                        {
                                                            "name": "node name 14",
                                                            "type": "node type 2",
                                                            "id": "tn12F0A0A0A"
                                                        },
                                                        {
                                                            "name": "node name 15",
                                                            "type": "node type 2",
                                                            "id": "tn12F0A0A0B"
                                                        },
                                                        {
                                                            "name": "node name 16",
                                                            "type": "node type 7",
                                                            "id": "tn12F0A0A0C",
                                                            "children": [
                                                                {
                                                                    "name": "node name 17",
                                                                    "type": "node type 2",
                                                                    "id": "tn12F0A0A0C0",
                                                                    "children": [
                                                                        {
                                                                            "name": "node name 18",
                                                                            "type": "node type 4",
                                                                            "id": "tn12F0A0A0C0A",
                                                                            "children": [
                                                                                {
                                                                                    "name": "node name 19",
                                                                                    "type": "node type 1",
                                                                                    "id": "tn12F0A0A0C0A0",
                                                                                    "children": [
                                                                                        {
                                                                                            "name": "node name 20",
                                                                                            "type": "node type 7",
                                                                                            "id": "tn12F0A0A0C0A0A",
                                                                                            "children": [
                                                                                                {
                                                                                                    "name": "node name 21",
                                                                                                    "type": "node type 6",
                                                                                                    "id": "tn12F0A0A0C0A0A0"
                                                                                                }
                                                                                            ]
                                                                                        },
                                                                                        {
                                                                                            "name": "node name 22",
                                                                                            "type": "node type 2",
                                                                                            "id": "tn12F0A0A0C0A0B"
                                                                                        },
                                                                                        {
                                                                                            "name": "node name 23",
                                                                                            "type": "node type 5",
                                                                                            "id": "tn12F0A0A0C0A0C",
                                                                                            "children": [
                                                                                                {
                                                                                                    "name": "node name 24",
                                                                                                    "type": "node type 7",
                                                                                                    "id": "tn12F0A0A0C0A0C0",
                                                                                                    "children": [
                                                                                                        {
                                                                                                            "name": "node name 25",
                                                                                                            "type": "node type 7",
                                                                                                            "id": "tn12F0A0A0C0A0C0A",
                                                                                                            "children": [
                                                                                                                {
                                                                                                                    "name": "node name 26",
                                                                                                                    "type": "node type 4",
                                                                                                                    "id": "tn12F0A0A0C0A0C0A0"
                                                                                                                }
                                                                                                            ]
                                                                                                        },
                                                                                                        {
                                                                                                            "name": "node name 27",
                                                                                                            "type": "node type 5",
                                                                                                            "id": "tn12F0A0A0C0A0C0B",
                                                                                                            "children": [
                                                                                                                {
                                                                                                                    "name": "node name 28",
                                                                                                                    "type": "node type 5",
                                                                                                                    "id": "tn12F0A0A0C0A0C0B0"
                                                                                                                },
                                                                                                                {
                                                                                                                    "name": "node name 29",
                                                                                                                    "type": "node type 3",
                                                                                                                    "id": "tn12F0A0A0C0A0C0B1"
                                                                                                                },
                                                                                                                {
                                                                                                                    "name": "node name 30",
                                                                                                                    "type": "node type 5",
                                                                                                                    "id": "tn12F0A0A0C0A0C0B2"
                                                                                                                },
                                                                                                                {
                                                                                                                    "name": "node name 31",
                                                                                                                    "type": "node type 5",
                                                                                                                    "id": "tn12F0A0A0C0A0C0B3"
                                                                                                                }
                                                                                                            ]
                                                                                                        }
                                                                                                    ]
                                                                                                }
                                                                                            ]
                                                                                        },
                                                                                        {
                                                                                            "name": "node name 32",
                                                                                            "type": "node type 1",
                                                                                            "id": "tn12F0A0A0C0A0D",
                                                                                            "children": [
                                                                                                {
                                                                                                    "name": "node name 33",
                                                                                                    "type": "node type 1",
                                                                                                    "id": "tn12F0A0A0C0A0D0"
                                                                                                }
                                                                                            ]
                                                                                        },
                                                                                        {
                                                                                            "name": "node name 34",
                                                                                            "type": "node type 7",
                                                                                            "id": "tn12F0A0A0C0A0E"
                                                                                        },
                                                                                        {
                                                                                            "name": "node name 35",
                                                                                            "type": "node type 2",
                                                                                            "id": "tn12F0A0A0C0A0F"
                                                                                        },
                                                                                        {
                                                                                            "name": "node name 36",
                                                                                            "type": "node type 5",
                                                                                            "id": "tn12F0A0A0C0A0G",
                                                                                            "children": [
                                                                                                {
                                                                                                    "name": "node name 37",
                                                                                                    "type": "node type 3",
                                                                                                    "id": "tn12F0A0A0C0A0G0",
                                                                                                    "children": [
                                                                                                        {
                                                                                                            "name": "node name 38",
                                                                                                            "type": "node type 5",
                                                                                                            "id": "tn12F0A0A0C0A0G0A",
                                                                                                            "children": [
                                                                                                                {
                                                                                                                    "name": "node name 39",
                                                                                                                    "type": "node type 7",
                                                                                                                    "id": "tn12F0A0A0C0A0G0A0"
                                                                                                                },
                                                                                                                {
                                                                                                                    "name": "node name 40",
                                                                                                                    "type": "node type 2",
                                                                                                                    "id": "tn12F0A0A0C0A0G0A1"
                                                                                                                },
                                                                                                                {
                                                                                                                    "name": "node name 41",
                                                                                                                    "type": "node type 4",
                                                                                                                    "id": "tn12F0A0A0C0A0G0A2"
                                                                                                                },
                                                                                                                {
                                                                                                                    "name": "node name 42",
                                                                                                                    "type": "node type 6",
                                                                                                                    "id": "tn12F0A0A0C0A0G0A3"
                                                                                                                }
                                                                                                            ]
                                                                                                        }
                                                                                                    ]
                                                                                                },
                                                                                                {
                                                                                                    "name": "node name 43",
                                                                                                    "type": "node type 4",
                                                                                                    "id": "tn12F0A0A0C0A0G1"
                                                                                                },
                                                                                                {
                                                                                                    "name": "node name 44",
                                                                                                    "type": "node type 5",
                                                                                                    "id": "tn12F0A0A0C0A0G2"
                                                                                                },
                                                                                                {
                                                                                                    "name": "node name 45",
                                                                                                    "type": "node type 6",
                                                                                                    "id": "tn12F0A0A0C0A0G3"
                                                                                                }
                                                                                            ]
                                                                                        }
                                                                                    ]
                                                                                },
                                                                                {
                                                                                    "name": "node name 46",
                                                                                    "type": "node type 6",
                                                                                    "id": "tn12F0A0A0C0A1",
                                                                                    "children": [
                                                                                        {
                                                                                            "name": "node name 47",
                                                                                            "type": "node type 1",
                                                                                            "id": "tn12F0A0A0C0A1A",
                                                                                            "children": [
                                                                                                {
                                                                                                    "name": "node name 48",
                                                                                                    "type": "node type 3",
                                                                                                    "id": "tn12F0A0A0C0A1A0",
                                                                                                    "children": [
                                                                                                        {
                                                                                                            "name": "node name 49",
                                                                                                            "type": "node type 7",
                                                                                                            "id": "tn12F0A0A0C0A1A0A",
                                                                                                            "children": [
                                                                                                                {
                                                                                                                    "name": "node name 50",
                                                                                                                    "type": "node type 7",
                                                                                                                    "id": "tn12F0A0A0C0A1A0A0"
                                                                                                                },
                                                                                                                {
                                                                                                                    "name": "node name 51",
                                                                                                                    "type": "node type 3",
                                                                                                                    "id": "tn12F0A0A0C0A1A0A1"
                                                                                                                },
                                                                                                                {
                                                                                                                    "name": "node name 52",
                                                                                                                    "type": "node type 7",
                                                                                                                    "id": "tn12F0A0A0C0A1A0A2"
                                                                                                                },
                                                                                                                {
                                                                                                                    "name": "node name 53",
                                                                                                                    "type": "node type 2",
                                                                                                                    "id": "tn12F0A0A0C0A1A0A3"
                                                                                                                },
                                                                                                                {
                                                                                                                    "name": "node name 54",
                                                                                                                    "type": "node type 1",
                                                                                                                    "id": "tn12F0A0A0C0A1A0A4"
                                                                                                                }
                                                                                                            ]
                                                                                                        }
                                                                                                    ]
                                                                                                },
                                                                                                {
                                                                                                    "name": "node name 55",
                                                                                                    "type": "node type 7",
                                                                                                    "id": "tn12F0A0A0C0A1A1"
                                                                                                },
                                                                                                {
                                                                                                    "name": "node name 56",
                                                                                                    "type": "node type 3",
                                                                                                    "id": "tn12F0A0A0C0A1A2",
                                                                                                    "children": [
                                                                                                        {
                                                                                                            "name": "node name 57",
                                                                                                            "type": "node type 3",
                                                                                                            "id": "tn12F0A0A0C0A1A2A"
                                                                                                        },
                                                                                                        {
                                                                                                            "name": "node name 58",
                                                                                                            "type": "node type 2",
                                                                                                            "id": "tn12F0A0A0C0A1A2B",
                                                                                                            "children": [
                                                                                                                {
                                                                                                                    "name": "node name 59",
                                                                                                                    "type": "node type 7",
                                                                                                                    "id": "tn12F0A0A0C0A1A2B0"
                                                                                                                },
                                                                                                                {
                                                                                                                    "name": "node name 60",
                                                                                                                    "type": "node type 1",
                                                                                                                    "id": "tn12F0A0A0C0A1A2B1"
                                                                                                                }
                                                                                                            ]
                                                                                                        }
                                                                                                    ]
                                                                                                },
                                                                                                {
                                                                                                    "name": "node name 61",
                                                                                                    "type": "node type 2",
                                                                                                    "id": "tn12F0A0A0C0A1A3"
                                                                                                }
                                                                                            ]
                                                                                        }
                                                                                    ]
                                                                                }
                                                                            ]
                                                                        },
                                                                        {
                                                                            "name": "node name 62",
                                                                            "type": "node type 5",
                                                                            "id": "tn12F0A0A0C0B",
                                                                            "children": [
                                                                                {
                                                                                    "name": "node name 63",
                                                                                    "type": "node type 5",
                                                                                    "id": "tn12F0A0A0C0B0",
                                                                                    "children": [
                                                                                        {
                                                                                            "name": "node name 64",
                                                                                            "type": "node type 6",
                                                                                            "id": "tn12F0A0A0C0B0A",
                                                                                            "children": [
                                                                                                {
                                                                                                    "name": "node name 65",
                                                                                                    "type": "node type 2",
                                                                                                    "id": "tn12F0A0A0C0B0A0",
                                                                                                    "children": [
                                                                                                        {
                                                                                                            "name": "node name 66",
                                                                                                            "type": "node type 2",
                                                                                                            "id": "tn12F0A0A0C0B0A0A"
                                                                                                        },
                                                                                                        {
                                                                                                            "name": "node name 67",
                                                                                                            "type": "node type 4",
                                                                                                            "id": "tn12F0A0A0C0B0A0B",
                                                                                                            "children": [
                                                                                                                {
                                                                                                                    "name": "node name 68",
                                                                                                                    "type": "node type 1",
                                                                                                                    "id": "tn12F0A0A0C0B0A0B0"
                                                                                                                }
                                                                                                            ]
                                                                                                        }
                                                                                                    ]
                                                                                                }
                                                                                            ]
                                                                                        }
                                                                                    ]
                                                                                },
                                                                                {
                                                                                    "name": "node name 69",
                                                                                    "type": "node type 6",
                                                                                    "id": "tn12F0A0A0C0B1",
                                                                                    "children": [
                                                                                        {
                                                                                            "name": "node name 70",
                                                                                            "type": "node type 3",
                                                                                            "id": "tn12F0A0A0C0B1A"
                                                                                        }
                                                                                    ]
                                                                                },
                                                                                {
                                                                                    "name": "node name 71",
                                                                                    "type": "node type 7",
                                                                                    "id": "tn12F0A0A0C0B2"
                                                                                },
                                                                                {
                                                                                    "name": "node name 72",
                                                                                    "type": "node type 5",
                                                                                    "id": "tn12F0A0A0C0B3"
                                                                                },
                                                                                {
                                                                                    "name": "node name 73",
                                                                                    "type": "node type 5",
                                                                                    "id": "tn12F0A0A0C0B4"
                                                                                },
                                                                                {
                                                                                    "name": "node name 74",
                                                                                    "type": "node type 7",
                                                                                    "id": "tn12F0A0A0C0B5",
                                                                                    "children": [
                                                                                        {
                                                                                            "name": "node name 75",
                                                                                            "type": "node type 3",
                                                                                            "id": "tn12F0A0A0C0B5A",
                                                                                            "children": [
                                                                                                {
                                                                                                    "name": "node name 76",
                                                                                                    "type": "node type 4",
                                                                                                    "id": "tn12F0A0A0C0B5A0"
                                                                                                },
                                                                                                {
                                                                                                    "name": "node name 77",
                                                                                                    "type": "node type 5",
                                                                                                    "id": "tn12F0A0A0C0B5A1"
                                                                                                },
                                                                                                {
                                                                                                    "name": "node name 78",
                                                                                                    "type": "node type 5",
                                                                                                    "id": "tn12F0A0A0C0B5A2"
                                                                                                },
                                                                                                {
                                                                                                    "name": "node name 79",
                                                                                                    "type": "node type 5",
                                                                                                    "id": "tn12F0A0A0C0B5A3",
                                                                                                    "children": [
                                                                                                        {
                                                                                                            "name": "node name 80",
                                                                                                            "type": "node type 2",
                                                                                                            "id": "tn12F0A0A0C0B5A3A",
                                                                                                            "children": [
                                                                                                                {
                                                                                                                    "name": "node name 81",
                                                                                                                    "type": "node type 7",
                                                                                                                    "id": "tn12F0A0A0C0B5A3A0"
                                                                                                                },
                                                                                                                {
                                                                                                                    "name": "node name 82",
                                                                                                                    "type": "node type 2",
                                                                                                                    "id": "tn12F0A0A0C0B5A3A1"
                                                                                                                },
                                                                                                                {
                                                                                                                    "name": "node name 83",
                                                                                                                    "type": "node type 2",
                                                                                                                    "id": "tn12F0A0A0C0B5A3A2"
                                                                                                                }
                                                                                                            ]
                                                                                                        },
                                                                                                        {
                                                                                                            "name": "node name 84",
                                                                                                            "type": "node type 1",
                                                                                                            "id": "tn12F0A0A0C0B5A3B"
                                                                                                        },
                                                                                                        {
                                                                                                            "name": "node name 85",
                                                                                                            "type": "node type 4",
                                                                                                            "id": "tn12F0A0A0C0B5A3C"
                                                                                                        },
                                                                                                        {
                                                                                                            "name": "node name 86",
                                                                                                            "type": "node type 5",
                                                                                                            "id": "tn12F0A0A0C0B5A3D",
                                                                                                            "children": [
                                                                                                                {
                                                                                                                    "name": "node name 87",
                                                                                                                    "type": "node type 6",
                                                                                                                    "id": "tn12F0A0A0C0B5A3D0"
                                                                                                                }
                                                                                                            ]
                                                                                                        }
                                                                                                    ]
                                                                                                }
                                                                                            ]
                                                                                        },
                                                                                        {
                                                                                            "name": "node name 88",
                                                                                            "type": "node type 5",
                                                                                            "id": "tn12F0A0A0C0B5B",
                                                                                            "children": [
                                                                                                {
                                                                                                    "name": "node name 89",
                                                                                                    "type": "node type 1",
                                                                                                    "id": "tn12F0A0A0C0B5B0",
                                                                                                    "children": [
                                                                                                        {
                                                                                                            "name": "node name 90",
                                                                                                            "type": "node type 2",
                                                                                                            "id": "tn12F0A0A0C0B5B0A",
                                                                                                            "children": [
                                                                                                                {
                                                                                                                    "name": "node name 91",
                                                                                                                    "type": "node type 3",
                                                                                                                    "id": "tn12F0A0A0C0B5B0A0"
                                                                                                                },
                                                                                                                {
                                                                                                                    "name": "node name 92",
                                                                                                                    "type": "node type 1",
                                                                                                                    "id": "tn12F0A0A0C0B5B0A1"
                                                                                                                },
                                                                                                                {
                                                                                                                    "name": "node name 93",
                                                                                                                    "type": "node type 6",
                                                                                                                    "id": "tn12F0A0A0C0B5B0A2"
                                                                                                                }
                                                                                                            ]
                                                                                                        },
                                                                                                        {
                                                                                                            "name": "node name 94",
                                                                                                            "type": "node type 5",
                                                                                                            "id": "tn12F0A0A0C0B5B0B",
                                                                                                            "children": [
                                                                                                                {
                                                                                                                    "name": "node name 95",
                                                                                                                    "type": "node type 7",
                                                                                                                    "id": "tn12F0A0A0C0B5B0B0"
                                                                                                                }
                                                                                                            ]
                                                                                                        },
                                                                                                        {
                                                                                                            "name": "node name 96",
                                                                                                            "type": "node type 7",
                                                                                                            "id": "tn12F0A0A0C0B5B0C",
                                                                                                            "children": [
                                                                                                                {
                                                                                                                    "name": "node name 97",
                                                                                                                    "type": "node type 7",
                                                                                                                    "id": "tn12F0A0A0C0B5B0C0"
                                                                                                                },
                                                                                                                {
                                                                                                                    "name": "node name 98",
                                                                                                                    "type": "node type 3",
                                                                                                                    "id": "tn12F0A0A0C0B5B0C1"
                                                                                                                }
                                                                                                            ]
                                                                                                        }
                                                                                                    ]
                                                                                                }
                                                                                            ]
                                                                                        },
                                                                                        {
                                                                                            "name": "node name 99",
                                                                                            "type": "node type 1",
                                                                                            "id": "tn12F0A0A0C0B5C"
                                                                                        },
                                                                                        {
                                                                                            "name": "node name 100",
                                                                                            "type": "node type 4",
                                                                                            "id": "tn12F0A0A0C0B5D",
                                                                                            "children": [
                                                                                                {
                                                                                                    "name": "node name 101",
                                                                                                    "type": "node type 7",
                                                                                                    "id": "tn12F0A0A0C0B5D0"
                                                                                                },
                                                                                                {
                                                                                                    "name": "node name 102",
                                                                                                    "type": "node type 2",
                                                                                                    "id": "tn12F0A0A0C0B5D1"
                                                                                                }
                                                                                            ]
                                                                                        },
                                                                                        {
                                                                                            "name": "node name 103",
                                                                                            "type": "node type 2",
                                                                                            "id": "tn12F0A0A0C0B5E"
                                                                                        },
                                                                                        {
                                                                                            "name": "node name 104",
                                                                                            "type": "node type 6",
                                                                                            "id": "tn12F0A0A0C0B5F",
                                                                                            "children": [
                                                                                                {
                                                                                                    "name": "node name 105",
                                                                                                    "type": "node type 5",
                                                                                                    "id": "tn12F0A0A0C0B5F0"
                                                                                                }
                                                                                            ]
                                                                                        }
                                                                                    ]
                                                                                }
                                                                            ]
                                                                        }
                                                                    ]
                                                                },
                                                                {
                                                                    "name": "node name 106",
                                                                    "type": "node type 6",
                                                                    "id": "tn12F0A0A0C1",
                                                                    "children": [
                                                                        {
                                                                            "name": "node name 107",
                                                                            "type": "node type 5",
                                                                            "id": "tn12F0A0A0C1A"
                                                                        }
                                                                    ]
                                                                },
                                                                {
                                                                    "name": "node name 108",
                                                                    "type": "node type 2",
                                                                    "id": "tn12F0A0A0C2"
                                                                },
                                                                {
                                                                    "name": "node name 109",
                                                                    "type": "node type 5",
                                                                    "id": "tn12F0A0A0C3"
                                                                }
                                                            ]
                                                        },
                                                        {
                                                            "name": "node name 110",
                                                            "type": "node type 2",
                                                            "id": "tn12F0A0A0D",
                                                            "children": [
                                                                {
                                                                    "name": "node name 111",
                                                                    "type": "node type 1",
                                                                    "id": "tn12F0A0A0D0"
                                                                },
                                                                {
                                                                    "name": "node name 112",
                                                                    "type": "node type 3",
                                                                    "id": "tn12F0A0A0D1",
                                                                    "children": [
                                                                        {
                                                                            "name": "node name 113",
                                                                            "type": "node type 3",
                                                                            "id": "tn12F0A0A0D1A",
                                                                            "children": [
                                                                                {
                                                                                    "name": "node name 114",
                                                                                    "type": "node type 1",
                                                                                    "id": "tn12F0A0A0D1A0"
                                                                                },
                                                                                {
                                                                                    "name": "node name 115",
                                                                                    "type": "node type 3",
                                                                                    "id": "tn12F0A0A0D1A1",
                                                                                    "children": [
                                                                                        {
                                                                                            "name": "node name 116",
                                                                                            "type": "node type 1",
                                                                                            "id": "tn12F0A0A0D1A1A",
                                                                                            "children": [
                                                                                                {
                                                                                                    "name": "node name 117",
                                                                                                    "type": "node type 3",
                                                                                                    "id": "tn12F0A0A0D1A1A0",
                                                                                                    "children": [
                                                                                                        {
                                                                                                            "name": "node name 118",
                                                                                                            "type": "node type 5",
                                                                                                            "id": "tn12F0A0A0D1A1A0A",
                                                                                                            "children": [
                                                                                                                {
                                                                                                                    "name": "node name 119",
                                                                                                                    "type": "node type 6",
                                                                                                                    "id": "tn12F0A0A0D1A1A0A0"
                                                                                                                },
                                                                                                                {
                                                                                                                    "name": "node name 120",
                                                                                                                    "type": "node type 5",
                                                                                                                    "id": "tn12F0A0A0D1A1A0A1"
                                                                                                                }
                                                                                                            ]
                                                                                                        },
                                                                                                        {
                                                                                                            "name": "node name 121",
                                                                                                            "type": "node type 5",
                                                                                                            "id": "tn12F0A0A0D1A1A0B"
                                                                                                        },
                                                                                                        {
                                                                                                            "name": "node name 122",
                                                                                                            "type": "node type 1",
                                                                                                            "id": "tn12F0A0A0D1A1A0C"
                                                                                                        },
                                                                                                        {
                                                                                                            "name": "node name 123",
                                                                                                            "type": "node type 3",
                                                                                                            "id": "tn12F0A0A0D1A1A0D"
                                                                                                        }
                                                                                                    ]
                                                                                                }
                                                                                            ]
                                                                                        }
                                                                                    ]
                                                                                },
                                                                                {
                                                                                    "name": "node name 124",
                                                                                    "type": "node type 7",
                                                                                    "id": "tn12F0A0A0D1A2",
                                                                                    "children": [
                                                                                        {
                                                                                            "name": "node name 125",
                                                                                            "type": "node type 5",
                                                                                            "id": "tn12F0A0A0D1A2A",
                                                                                            "children": [
                                                                                                {
                                                                                                    "name": "node name 126",
                                                                                                    "type": "node type 2",
                                                                                                    "id": "tn12F0A0A0D1A2A0"
                                                                                                },
                                                                                                {
                                                                                                    "name": "node name 127",
                                                                                                    "type": "node type 1",
                                                                                                    "id": "tn12F0A0A0D1A2A1"
                                                                                                },
                                                                                                {
                                                                                                    "name": "node name 128",
                                                                                                    "type": "node type 1",
                                                                                                    "id": "tn12F0A0A0D1A2A2"
                                                                                                }
                                                                                            ]
                                                                                        },
                                                                                        {
                                                                                            "name": "node name 129",
                                                                                            "type": "node type 3",
                                                                                            "id": "tn12F0A0A0D1A2B",
                                                                                            "children": [
                                                                                                {
                                                                                                    "name": "node name 130",
                                                                                                    "type": "node type 4",
                                                                                                    "id": "tn12F0A0A0D1A2B0"
                                                                                                }
                                                                                            ]
                                                                                        },
                                                                                        {
                                                                                            "name": "node name 131",
                                                                                            "type": "node type 7",
                                                                                            "id": "tn12F0A0A0D1A2C"
                                                                                        }
                                                                                    ]
                                                                                }
                                                                            ]
                                                                        },
                                                                        {
                                                                            "name": "node name 132",
                                                                            "type": "node type 2",
                                                                            "id": "tn12F0A0A0D1B",
                                                                            "children": [
                                                                                {
                                                                                    "name": "node name 133",
                                                                                    "type": "node type 6",
                                                                                    "id": "tn12F0A0A0D1B0",
                                                                                    "children": [
                                                                                        {
                                                                                            "name": "node name 134",
                                                                                            "type": "node type 4",
                                                                                            "id": "tn12F0A0A0D1B0A",
                                                                                            "children": [
                                                                                                {
                                                                                                    "name": "node name 135",
                                                                                                    "type": "node type 7",
                                                                                                    "id": "tn12F0A0A0D1B0A0",
                                                                                                    "children": [
                                                                                                        {
                                                                                                            "name": "node name 136",
                                                                                                            "type": "node type 7",
                                                                                                            "id": "tn12F0A0A0D1B0A0A",
                                                                                                            "children": [
                                                                                                                {
                                                                                                                    "name": "node name 137",
                                                                                                                    "type": "node type 1",
                                                                                                                    "id": "tn12F0A0A0D1B0A0A0"
                                                                                                                }
                                                                                                            ]
                                                                                                        }
                                                                                                    ]
                                                                                                },
                                                                                                {
                                                                                                    "name": "node name 138",
                                                                                                    "type": "node type 3",
                                                                                                    "id": "tn12F0A0A0D1B0A1"
                                                                                                },
                                                                                                {
                                                                                                    "name": "node name 139",
                                                                                                    "type": "node type 6",
                                                                                                    "id": "tn12F0A0A0D1B0A2"
                                                                                                },
                                                                                                {
                                                                                                    "name": "node name 140",
                                                                                                    "type": "node type 3",
                                                                                                    "id": "tn12F0A0A0D1B0A3"
                                                                                                }
                                                                                            ]
                                                                                        }
                                                                                    ]
                                                                                }
                                                                            ]
                                                                        },
                                                                        {
                                                                            "name": "node name 141",
                                                                            "type": "node type 2",
                                                                            "id": "tn12F0A0A0D1C",
                                                                            "children": [
                                                                                {
                                                                                    "name": "node name 142",
                                                                                    "type": "node type 6",
                                                                                    "id": "tn12F0A0A0D1C0"
                                                                                }
                                                                            ]
                                                                        },
                                                                        {
                                                                            "name": "node name 143",
                                                                            "type": "node type 1",
                                                                            "id": "tn12F0A0A0D1D"
                                                                        },
                                                                        {
                                                                            "name": "node name 144",
                                                                            "type": "node type 5",
                                                                            "id": "tn12F0A0A0D1E"
                                                                        }
                                                                    ]
                                                                },
                                                                {
                                                                    "name": "node name 145",
                                                                    "type": "node type 6",
                                                                    "id": "tn12F0A0A0D2"
                                                                },
                                                                {
                                                                    "name": "node name 146",
                                                                    "type": "node type 6",
                                                                    "id": "tn12F0A0A0D3",
                                                                    "children": [
                                                                        {
                                                                            "name": "node name 147",
                                                                            "type": "node type 4",
                                                                            "id": "tn12F0A0A0D3A"
                                                                        }
                                                                    ]
                                                                },
                                                                {
                                                                    "name": "node name 148",
                                                                    "type": "node type 6",
                                                                    "id": "tn12F0A0A0D4"
                                                                }
                                                            ]
                                                        },
                                                        {
                                                            "name": "node name 149",
                                                            "type": "node type 5",
                                                            "id": "tn12F0A0A0E",
                                                            "children": [
                                                                {
                                                                    "name": "node name 150",
                                                                    "type": "node type 4",
                                                                    "id": "tn12F0A0A0E0",
                                                                    "children": [
                                                                        {
                                                                            "name": "node name 151",
                                                                            "type": "node type 6",
                                                                            "id": "tn12F0A0A0E0A"
                                                                        }
                                                                    ]
                                                                },
                                                                {
                                                                    "name": "node name 152",
                                                                    "type": "node type 2",
                                                                    "id": "tn12F0A0A0E1"
                                                                }
                                                            ]
                                                        }
                                                    ]
                                                },
                                                {
                                                    "name": "node name 153",
                                                    "type": "node type 6",
                                                    "id": "tn12F0A0A1",
                                                    "children": [
                                                        {
                                                            "name": "node name 154",
                                                            "type": "node type 6",
                                                            "id": "tn12F0A0A1A"
                                                        },
                                                        {
                                                            "name": "node name 155",
                                                            "type": "node type 1",
                                                            "id": "tn12F0A0A1B",
                                                            "children": [
                                                                {
                                                                    "name": "node name 156",
                                                                    "type": "node type 7",
                                                                    "id": "tn12F0A0A1B0"
                                                                }
                                                            ]
                                                        },
                                                        {
                                                            "name": "node name 157",
                                                            "type": "node type 5",
                                                            "id": "tn12F0A0A1C"
                                                        }
                                                    ]
                                                }
                                            ]
                                        }
                                    ]
                                },
                                {
                                    "name": "node name 158",
                                    "type": "node type 4",
                                    "id": "tn12F0A1",
                                    "children": [
                                        {
                                            "name": "node name 159",
                                            "type": "node type 2",
                                            "id": "tn12F0A1A"
                                        }
                                    ]
                                },
                                {
                                    "name": "node name 160",
                                    "type": "node type 6",
                                    "id": "tn12F0A2",
                                    "children": [
                                        {
                                            "name": "node name 161",
                                            "type": "node type 4",
                                            "id": "tn12F0A2A"
                                        }
                                    ]
                                }
                            ]
                        }
                    ]
                },
                {
                    "name": "node name 162",
                    "type": "node type 6",
                    "id": "tn12F1",
                    "children": [
                        {
                            "name": "node name 163",
                            "type": "node type 3",
                            "id": "tn12F1A",
                            "children": [
                                {
                                    "name": "node name 164",
                                    "type": "node type 4",
                                    "id": "tn12F1A0"
                                }
                            ]
                        },
                        {
                            "name": "node name 165",
                            "type": "node type 6",
                            "id": "tn12F1B"
                        },
                        {
                            "name": "node name 166",
                            "type": "node type 7",
                            "id": "tn12F1C"
                        }
                    ]
                }
            ]
        },
        {
            "name": "node name 167",
            "type": "node type 2",
            "id": "tn12G"
        },
        {
            "name": "node name 168",
            "type": "node type 1",
            "id": "tn12H",
            "children": [
                {
                    "name": "node name 169",
                    "type": "node type 2",
                    "id": "tn12H0",
                    "children": [
                        {
                            "name": "node name 170",
                            "type": "node type 1",
                            "id": "tn12H0A"
                        }
                    ]
                }
            ]
        },
        {
            "name": "node name 171",
            "type": "node type 3",
            "id": "tn12I",
            "children": [
                {
                    "name": "node name 172",
                    "type": "node type 6",
                    "id": "tn12I0"
                }
            ]
        },
        {
            "name": "node name 173",
            "type": "node type 6",
            "id": "tn12J",
            "children": [
                {
                    "name": "node name 174",
                    "type": "node type 4",
                    "id": "tn12J0"
                }
            ]
        }
    ]
}